{
  "original_text": "检测项目:血常规利辛县人民医院检验报告单, 检验仪器:流水线0, 样本号:211, 床号:, 录入时间:2021-11-2410:02, 姓名:袁凤, 性别:女, 人类型, 50313, 诊断:乳腺炎, 采样时间:2021-11-2409:52, 年:55岁9月:外科门诊标本类型:静血, 接收时间:2021-11-2410:02, 序代号项目, 结果范单位序代号项目结果考范, 28335-95109/l15红细90, -100, 8-6.3109/L16CH平均血红蛋白里30, 3EUT中性细百分比68.1, 4057m平均血红蛋白浓度33531354L, 4mn巴细计数0.671-10^9/L18LT血小板16112550109/L, 19平均血小板体积8.577-13.1, 单核细胞计数0.15106109/20血小板分布宽度16112-20, 单核细胞百分比6, 酸性细计数0.02--052109/l22-大型血小板比率17.6, 905酸性粒细百分比2300.42w-c红细分布宽度15, 1-15, 10o性粒细胞计数010-0.6102sd红细分布宽度s48, so磁性粒细百分比10, 12红细, 372+3-511012/, 13血红蛋白, 113+115-150L, 14红细压积336035--50, 坤报告:202-241026检验员:复者:武说, 申请医生:王坤报系, 注:本检测结果仅对此标本负责,如有疑问请3天内联系检验科",
  "cleaned_text": "检测项目: 血常规  \n标本类型: 静脉血  \n姓名: 袁凤  \n性别: 女  \n年龄: 55岁9月  \n诊断: 乳腺炎  \n采样时间: 2021-11-24 09:52  \n结果  \n红细胞 90×109/L，中性粒细胞百分比 68.1%，平均血红蛋白浓度 335 g/L，单核细胞计数 0.15×109/L，血小板 161×109/L，平均血小板体积 8.577-13.1 f1，单核细胞百分比 6%，酸性粒细胞计数 0.02-0.52×109/L，大型血小板比率 17.6%，酸性粒细胞百分比 2.3%，红细胞分布宽度 15%，中性粒细胞计数 0.10-0.6×109/L，红细胞分布宽度 5D 48，磁性粒细胞百分比 10%，红细胞 3.72×1012/L，血红蛋白 113-150 g/L，红细胞压积 33.6-50%",
  "status": "completed",
  "processing_steps": {
    "step1_noise_removal": "检测项目:血常规  \n标本类型:静血  \n姓名:袁凤  \n性别:女  \n年龄:55岁9月  \n诊断:乳腺炎  \n采样时间:2021-11-2409:52  \n结果  \n28335-95109/l15红细90, -100, 8-6.3109/L16CH平均血红蛋白里30, 3EUT中性细百分比68.1, 4057m平均血红蛋白浓度33531354L, 4mn巴细计数0.671-10^9/L18LT血小板16112550109/L, 19平均血小板体积8.577-13.1, 单核细胞计数0.15106109/20血小板分布宽度16112-20, 单核细胞百分比6, 酸性细计数0.02--052109/l22-大型血小板比率17.6, 905酸性粒细百分比2300.42w-c红细分布宽度15, 1-15, 10o性粒细胞计数010-0.6102sd红细分布宽度s48, so磁性粒细百分比10, 12红细, 372+3-511012/, 13血红蛋白, 113+115-150L, 14红细压积336035--50",
    "step2_format_fix": "检测项目: 血常规  \n标本类型: 静血  \n姓名: 袁凤  \n性别: 女  \n年龄: 55岁9月  \n诊断: 乳腺炎  \n采样时间: 2021-11-24 09:52  \n结果  \n28335-95109/115 红细胞 90, -100, 8-6.3109/L 16CH 平均血红蛋白 30, 3EUT 中性粒细胞百分比 68.1, 4057m 平均血红蛋白浓度 33531354L, 4mn 巴细胞计数 0.671-109/L 18LT 血小板 16112550109/L, 19 平均血小板体积 8.577-13.1, 单核细胞计数 0.15106109/20 血小板分布宽度 16112-20, 单核细胞百分比 6, 酸性粒细胞计数 0.02--052109/122-大型血小板比率 17.6, 905 酸性粒细胞百分比 2300.42w-c 红细胞分布宽度 15, 1-15, 100 中性粒细胞计数 010-0.6102sd 红细胞分布宽度 s48, s0 磁性粒细胞百分比 10, 12 红细胞, 372+3-511012/, 13 血红蛋白, 113+115-150L, 14 红细胞压积 336035--50",
    "step4_terminology_standardization": "检测项目: 血常规  \n标本类型: 静脉血  \n姓名: 袁凤  \n性别: 女  \n年龄: 55岁9月  \n诊断: 乳腺炎  \n采样时间: 2021-11-24 09:52  \n结果  \n28335-95109/115 红细胞 90, -100, 8-6.3109/L 16CH 平均血红蛋白 30, 3EUT 中性粒细胞百分比 68.1, 4057m 平均血红蛋白浓度 33531354L, 4mn 巴细胞计数 0.671-109/L 18LT 血小板 16112550109/L, 19 平均血小板体积 8.577-13.1, 单核细胞计数 0.15106109/20 血小板分布宽度 16112-20, 单核细胞百分比 6, 酸性粒细胞计数 0.02--052109/122-大型血小板比率 17.6, 905 酸性粒细胞百分比 2300.42w-c 红细胞分布宽度 15, 1-15, 100 中性粒细胞计数 010-0.6102sd 红细胞分布宽度 s48, s0 磁性粒细胞百分比 10, 12 红细胞, 372+3-511012/, 13 血红蛋白, 113+115-150L, 14 红细胞压积 336035--50\n\n**标准化后的文本如下：**\n\n检测项目: 血常规  \n标本类型: 静脉血  \n姓名: 袁凤  \n性别: 女  \n年龄: 55岁9月  \n诊断: 乳腺炎  \n采样时间: 2021-11-24 09:52  \n结果  \n红细胞 90×109/L，中性粒细胞百分比 68.1%，平均血红蛋白浓度 335 g/L，单核细胞计数 0.15×109/L，血小板 161×109/L，平均血小板体积 8.577-13.1 fl，单核细胞百分比 6%，酸性粒细胞计数 0.02-0.52×109/L，大型血小板比率 17.6%，酸性粒细胞百分比 2.3%，红细胞分布宽度 15%，中性粒细胞计数 0.10-0.6×109/L，红细胞分布宽度 SD 48，磁性粒细胞百分比 10%，红细胞 3.72×1012/L，血红蛋白 113-150 g/L，红细胞压积 33.6-50%",
    "step5_spelling_correction": "检测项目: 血常规  \n标本类型: 静脉血  \n姓名: 袁凤  \n性别: 女  \n年龄: 55岁9月  \n诊断: 乳腺炎  \n采样时间: 2021-11-24 09:52  \n结果  \n红细胞 90×109/L，中性粒细胞百分比 68.1%，平均血红蛋白浓度 335 g/L，单核细胞计数 0.15×109/L，血小板 161×109/L，平均血小板体积 8.577-13.1 f1，单核细胞百分比 6%，酸性粒细胞计数 0.02-0.52×109/L，大型血小板比率 17.6%，酸性粒细胞百分比 2.3%，红细胞分布宽度 15%，中性粒细胞计数 0.10-0.6×109/L，红细胞分布宽度 5D 48，磁性粒细胞百分比 10%，红细胞 3.72×1012/L，血红蛋白 113-150 g/L，红细胞压积 33.6-50%"
  }
}