{
  "structured": {
    "年龄": "24",
    "绝经状态": "否",
    "PS": "4",
    "IV期": "否",
    "M1分期": "否",
    "远处转移": "是",
    "转移位置": "脑,其他",
    "转移或复发": "是",
    "复发": "否",
    "是否保乳": "否",
    "已行根治手术": "是",
    "可再次手术": "否",
    "切缘<1mm": "是",
    "切缘阳性": "否",
    "是否腋窝清扫": "是",
    "腋窝淋巴结是否有阳性": "否",
    "腋窝淋巴结阳性个数(术前)": "",
    "腋窝淋巴结阳性个数(术后)": "20",
    "根治手术时间": "2022-08-06",
    "肿块大小CM(术前)": 8.6,
    "肿块大小CM(术后)": 6.8,
    "术前肿块大小CM(CT)": 8.6,
    "术前肿块大小CM(MRI)": "",
    "术前肿块大小CM(B超)": "",
    "术前肿块大小CM(查体)": "",
    "术后肿块大小CM(CT)": 6.6,
    "术后肿块大小CM(MRI)": 6.8,
    "术后肿块大小CM(B超)": 6.4,
    "术后肿块大小CM(查体)": 3.6,
    "DFS（月）": "8",
    "复发时间": "2011-01-12",
    "药品信息": [
      "多西他赛方案",
      "部分乳腺照射 (PBI)方案"
    ],
    "免疫禁忌": "否",
    "有新辅助治疗": "否",
    "新辅助治疗使用免疫": "",
    "新辅助治疗使用双靶": "",
    "cTNM": "cT2N1M0",
    "pTNM": "",
    "ypTNM": "ypT3N3M1",
    "患者": "刘**"
  },
  "text": "刘**，女，24岁，未绝经，PS评分4分，IV期及M1分期均为阴性。\n2022年8月6日行根治手术，术中行腋窝淋巴结清扫，术后病理示腋窝淋巴结阳性20个，切缘阴性。\n术前肿块大小8.6cm，术后CT测量6.6cm，MRI测量6.8cm，B超测量6.4cm，查体测量3.6cm。\n术后接受多西他赛联合部分乳腺照射（PBI）治疗，DFS为8个月。\n未行新辅助治疗，无免疫治疗及双靶治疗使用记录。\n2021年1月12日复发，伴脑及其他部位转移。",
  "noisy_text": "中行腋窝淋巴结清扫，术后病理示腋窝淋巴结阳性20个，切缘阴性。术前肿块大小8·6cm，术后CT测量6·6cm，MRI测量6·8cm，B超测量6·4cm，查体测量3·6cm。术后接受多西他赛联合部→分乳腺照射（PBI）治疗，DFS"
}