{
  "structured": {
    "年龄": "39",
    "绝经状态": "否",
    "PS": "1",
    "IV期": "否",
    "M1分期": "是",
    "远处转移": "是",
    "转移位置": "脑,肝,其他",
    "转移或复发": "是",
    "复发": "否",
    "是否保乳": "是",
    "已行根治手术": "",
    "可再次手术": "否",
    "切缘<1mm": "是",
    "切缘阳性": "是",
    "是否腋窝清扫": "",
    "腋窝淋巴结是否有阳性": "否",
    "腋窝淋巴结阳性个数(术前)": "",
    "腋窝淋巴结阳性个数(术后)": "",
    "根治手术时间": "",
    "肿块大小CM(术前)": 5.5,
    "肿块大小CM(术后)": 3.3,
    "术前肿块大小CM(CT)": 3.4,
    "术前肿块大小CM(MRI)": 5.5,
    "术前肿块大小CM(B超)": "",
    "术前肿块大小CM(查体)": 6.4,
    "术后肿块大小CM(CT)": 3.3,
    "术后肿块大小CM(MRI)": "",
    "术后肿块大小CM(B超)": 4.1,
    "术后肿块大小CM(查体)": "",
    "DFS（月）": "44",
    "复发时间": "2021-11-12",
    "pCR": "",
    "ypT0N0": "否",
    "MP评分": "1",
    "cTNM": "cT4N3M1",
    "pTNM": "pT4N3M1",
    "ypTNM": "ypT2N2M0",
    "患者": "马**"
  },
  "text": "马**，女，39岁，PS评分1分，IV期，伴M1转移。\n未绝经，行保乳手术。\n术前肿块大小5.5cm，术后缩小至3.3cm。\n2021年11月12日复发，伴脑、肝及多部位转移。\n切缘阳性，无远处转移。\ncTNM分期cT4N3M1，pTNM分期pT4N3M1，ypTNM分期ypT2N2M0。\nMP评分1分。",
  "noisy_text": "。 未绝经，行保乳手术。 术前肿块大小5.5cm，术后缩小至3.3cm。 2021年11月12日复发，伴脑、肝及多部位转移。 切缘阳性，无远处转移。 cTNM分期cT4N3M1，pTNM分期pT4N3M1，ypTNM分期ypT2N2M0。 MP评分1分。 项目名称：血红蛋 白 128g/L 115–150   项目名称：白细胞计数 6。8×10^9/L 4.0-10.0   项目名称：中性粒细胞绝对值 4。5×10^9/L 1.8-7.5   项目名称：淋巴细胞绝对值 1.2×10^9/L 0.8-4.0   项目名称：血小板计数 210×１0^9/L 100-300   项目名称：C反应蛋白 8.5 mg/L <5。0   项目名称：血清肌酐 82μmol/L　44－106  项目名称：尿素氮 6.3 mmol/L 2.5-8.3   项目名称：空腹血糖　6.1 mmol/L 3.9-6.1   项目名称：肺CT示双肺纹理增粗伴少许斑片影    \\n  　项目名称：血红蛋 白 128 g/L 115-１50  项目名称：白细胞计数 6.8×10^9/L　4。0-10.0   项目名称：中性粒细胞绝对值 4。5×10^9/L 1.8-7.5   项目名称：淋巴细胞绝对值 1.2×10^9/L 0.8-4。0   项目名称：血小板计数 210×I0^9/L10●-300   项目名称：C反应蛋白 8.5 mg/L <5.0  　项目名称：血清肌酐 82 μmol/L 44－106  项目名称：尿素氮 6.3　mmol/L "
}